cb_palettes/__init__.py
cb_palettes/builtin.py
cb_palettes/color.py
cb_palettes/palette.py
cb_palettes-0.1.1.dist-info/LICENSE
cb_palettes-0.1.1.dist-info/METADATA
cb_palettes-0.1.1.dist-info/WHEEL
cb_palettes-0.1.1.dist-info/top_level.txt
cb_palettes-0.1.1.dist-info/RECORD
