Metadata-Version: 2.1
Name: cb_palettes
Version: 0.1.1
Summary: A collection of cb-friendly color palettes
Author-email: Travis Kessler <travis.j.kessler@gmail.com>
Project-URL: Homepage, https://github.com/tjkessler/cb-palettes
Project-URL: Bug Tracker, https://github.com/tjkessler/cb-palettes/issues
Classifier: Programming Language :: Python :: 3.8
Classifier: License :: OSI Approved :: MIT License
Classifier: Operating System :: OS Independent
Requires-Python: >=3.8
License-File: LICENSE
